sgvalidator/VERSION
sgvalidator/__init__.py
sgvalidator/color_printer.py
sgvalidator/config.py
sgvalidator/data_preprocessor.py
sgvalidator/decorators.py
sgvalidator/runner_factory.py
sgvalidator/sgvalidator.py
sgvalidator/validator_config.py
sgvalidator/validator_io.py
sgvalidator/validator_runner.py
sgvalidator/runners/__init__.py
sgvalidator/runners/abstract_runner.py
sgvalidator/runners/column_validator_runner.py
sgvalidator/runners/dataframe_validator_runner.py
sgvalidator/runners/row_validator_runner.py
sgvalidator/runners/runner_factory.py
sgvalidator/tests/__init__.py
sgvalidator/tests/test_ca_country_validator.py
sgvalidator/tests/test_centroid_validator.py
sgvalidator/tests/test_column_validators.py
sgvalidator/tests/test_count_validator.py
sgvalidator/tests/test_country_detection.py
sgvalidator/tests/test_data.py
sgvalidator/tests/test_data_factory.py
sgvalidator/tests/test_dataframe_validators.py
sgvalidator/tests/test_duplication_validator.py
sgvalidator/tests/test_fill_rate_validator.py
sgvalidator/tests/test_geo_consistency_validator.py
sgvalidator/tests/test_latlng_country_validator.py
sgvalidator/tests/test_row_validators.py
sgvalidator/tests/test_schema_validator.py
sgvalidator/tests/test_store_number_column_validator.py
sgvalidator/tests/test_street_address_validator.py
sgvalidator/tests/test_trash_value_validator.py
sgvalidator/tests/test_us_country_validator.py
sgvalidator/tests/test_utils.py
sgvalidator/tests/utils.py
sgvalidator/types/__init__.py
sgvalidator/types/country_codes.py
sgvalidator/types/validator_response.py
sgvalidator/types/validator_status.py
sgvalidator/types/validator_types.py
sgvalidator/validators/IGNORE_MESSAGE.txt
sgvalidator/validators/__init__.py
sgvalidator/validators/abstract_validator.py
sgvalidator/validators/bad_centroid_tagger.py
sgvalidator/validators/blank_value_validator.py
sgvalidator/validators/centroid_validator.py
sgvalidator/validators/count_validator.py
sgvalidator/validators/country_validator.py
sgvalidator-0.0.71.dist-info/METADATA
sgvalidator-0.0.71.dist-info/WHEEL
sgvalidator-0.0.71.dist-info/top_level.txt
sgvalidator-0.0.71.dist-info/RECORD
