Metadata-Version: 2.1
Name: sgvalidator
Version: 0.0.71
Summary: UNKNOWN
Home-page: UNKNOWN
Author: noah
Author-email: info@safegraph.com
License: UNKNOWN
Platform: UNKNOWN
Requires-Dist: phonenumbers (==8.10.13)
Requires-Dist: zipcodes (==1.0.5)
Requires-Dist: us (==1.0.0)
Requires-Dist: usaddress
Requires-Dist: uszipcode
Requires-Dist: pandas
